gpt3prompts/__init__.py
gpt3prompts/api_key.py
gpt3prompts/gpttext.py
gpt3prompts/prompts.py
GPT3Prompts-0.0.7.dist-info/METADATA
GPT3Prompts-0.0.7.dist-info/WHEEL
GPT3Prompts-0.0.7.dist-info/top_level.txt
GPT3Prompts-0.0.7.dist-info/RECORD
