Metadata-Version: 2.1
Name: GPT3Prompts
Version: 0.0.7
Summary: GPT3 For Generator any Prompts AI Art Module 
Home-page: https://github.com/falahgs/
Author: Falahgs.G.Saleih
Author-email: falahgs07@gmail.com
License: MIT
Keywords: GPT-3,AI Art,Artificial Intelligence ,artist
Classifier: Programming Language :: Python :: 3
Classifier: License :: OSI Approved :: MIT License
Classifier: Operating System :: OS Independent
Requires-Python: >=3.6
Requires-Dist: openai
